docxmerge_sdk/__init__.py
docxmerge_sdk-1.2.0.dist-info/METADATA
docxmerge_sdk-1.2.0.dist-info/WHEEL
docxmerge_sdk-1.2.0.dist-info/top_level.txt
docxmerge_sdk-1.2.0.dist-info/RECORD
