Metadata-Version: 2.1
Name: docxmerge-sdk
Version: 1.2.0
Summary: Sdk for docxmerge
Home-page: https://github.com/Docxmerge/docxmerge-sdk
Author: David viejo pomata
Author-email: davidviejopomata@gmail.com
License: UNKNOWN
Platform: UNKNOWN
Classifier: Programming Language :: Python :: 3
Classifier: License :: OSI Approved :: MIT License
Classifier: Operating System :: OS Independent
Requires-Dist: requests
